randypy/__init__.py
randypy/randypy.py
randypy-0.1.2.dist-info/METADATA
randypy-0.1.2.dist-info/WHEEL
randypy-0.1.2.dist-info/top_level.txt
randypy-0.1.2.dist-info/RECORD
