Metadata-Version: 2.1
Name: randypy
Version: 0.1.2
Summary: A Python library for generating random data
Home-page: https://github.com/Dinogarlic/RandyPy
Author: dinogarlic
Author-email: xldpsl1003@gmail.com
Classifier: Programming Language :: Python :: 3
Classifier: License :: OSI Approved :: MIT License
Classifier: Operating System :: OS Independent
Requires-Python: >=3.6
